{
  "version": "1.0.0",
  "description": "Curated Google Fonts pairs for SaaS landing pages. Used by direction picker to constrain font choices to high-quality pairs. Last updated: 2026-05-01.",
  "pairs": [
    { "id": "inter-inter", "heading": "Inter", "body": "Inter", "style": "modern-minimal", "tags": ["tech", "saas", "clean", "neutral"] },
    { "id": "outfit-inter", "heading": "Outfit", "body": "Inter", "style": "modern-minimal", "tags": ["startup", "saas", "friendly"] },
    { "id": "plus-jakarta-sans-inter", "heading": "Plus Jakarta Sans", "body": "Inter", "style": "modern-minimal", "tags": ["saas", "tech", "professional"] },
    { "id": "outfit-outfit", "heading": "Outfit", "body": "Outfit", "style": "modern-minimal", "tags": ["consumer", "startup", "clean"] },
    { "id": "dm-sans-dm-sans", "heading": "DM Sans", "body": "DM Sans", "style": "humanist", "tags": ["saas", "fintech", "accessible"] },
    { "id": "work-sans-work-sans", "heading": "Work Sans", "body": "Work Sans", "style": "humanist", "tags": ["enterprise", "readable", "neutral"] },
    { "id": "nunito-sans-nunito-sans", "heading": "Nunito Sans", "body": "Nunito Sans", "style": "humanist", "tags": ["consumer", "warm", "approachable"] },
    { "id": "manrope-manrope", "heading": "Manrope", "body": "Manrope", "style": "geometric", "tags": ["tech", "modern", "saas"] },
    { "id": "sora-sora", "heading": "Sora", "body": "Sora", "style": "geometric", "tags": ["tech", "futuristic", "startup"] },
    { "id": "space-grotesk-inter", "heading": "Space Grotesk", "body": "Inter", "style": "geometric", "tags": ["developer", "tech", "distinctive"] },
    { "id": "playfair-display-lato", "heading": "Playfair Display", "body": "Lato", "style": "serif-forward", "tags": ["editorial", "premium", "brand"] },
    { "id": "dm-serif-display-dm-sans", "heading": "DM Serif Display", "body": "DM Sans", "style": "serif-forward", "tags": ["editorial", "contrast", "modern"] },
    { "id": "lora-source-sans-3", "heading": "Lora", "body": "Source Sans 3", "style": "editorial", "tags": ["editorial", "readable", "content"] },
    { "id": "cormorant-garamond-outfit", "heading": "Cormorant Garamond", "body": "Outfit", "style": "serif-forward", "tags": ["luxury", "premium", "elegant"] },
    { "id": "libre-baskerville-lato", "heading": "Libre Baskerville", "body": "Lato", "style": "editorial", "tags": ["trust", "finance", "professional"] },
    { "id": "ibm-plex-serif-ibm-plex-sans", "heading": "IBM Plex Serif", "body": "IBM Plex Sans", "style": "editorial", "tags": ["enterprise", "fintech", "systematic"] },
    { "id": "roboto-slab-roboto", "heading": "Roboto Slab", "body": "Roboto", "style": "geometric", "tags": ["enterprise", "technical", "systematic"] },
    { "id": "josefin-sans-josefin-sans", "heading": "Josefin Sans", "body": "Josefin Sans", "style": "geometric", "tags": ["minimal", "architectural", "fashion"] },
    { "id": "raleway-raleway", "heading": "Raleway", "body": "Raleway", "style": "geometric", "tags": ["design", "creative", "premium"] },
    { "id": "montserrat-open-sans", "heading": "Montserrat", "body": "Open Sans", "style": "geometric", "tags": ["enterprise", "corporate", "reliable"] },
    { "id": "poppins-poppins", "heading": "Poppins", "body": "Poppins", "style": "geometric", "tags": ["consumer", "startup", "playful"] },
    { "id": "urbanist-urbanist", "heading": "Urbanist", "body": "Urbanist", "style": "modern-minimal", "tags": ["tech", "modern", "clean"] },
    { "id": "lexend-lexend", "heading": "Lexend", "body": "Lexend", "style": "humanist", "tags": ["accessible", "reading", "saas"] },
    { "id": "figtree-figtree", "heading": "Figtree", "body": "Figtree", "style": "humanist", "tags": ["friendly", "startup", "consumer"] },
    { "id": "bricolage-grotesque-bricolage-grotesque", "heading": "Bricolage Grotesque", "body": "Bricolage Grotesque", "style": "geometric", "tags": ["editorial", "distinctive", "bold"] },
    { "id": "cabinet-grotesk-satoshi", "heading": "Cabinet Grotesk", "body": "Satoshi", "style": "geometric", "tags": ["startup", "modern", "tech"] },
    { "id": "bebas-neue-dm-sans", "heading": "Bebas Neue", "body": "DM Sans", "style": "geometric", "tags": ["bold", "sports", "consumer", "display"] },
    { "id": "space-mono-inter", "heading": "Space Mono", "body": "Inter", "style": "modern-minimal", "tags": ["developer", "mono-accent", "technical"] },
    { "id": "jetbrains-mono-inter", "heading": "JetBrains Mono", "body": "Inter", "style": "modern-minimal", "tags": ["developer", "devtools", "technical"] },
    { "id": "ibm-plex-mono-ibm-plex-sans", "heading": "IBM Plex Mono", "body": "IBM Plex Sans", "style": "editorial", "tags": ["developer", "enterprise", "systematic"] },
    { "id": "pt-serif-pt-sans", "heading": "PT Serif", "body": "PT Sans", "style": "editorial", "tags": ["news", "publishing", "trust"] },
    { "id": "merriweather-source-sans-3", "heading": "Merriweather", "body": "Source Sans 3", "style": "editorial", "tags": ["content", "publishing", "readable"] },
    { "id": "nunito-nunito", "heading": "Nunito", "body": "Nunito", "style": "humanist", "tags": ["education", "consumer", "friendly"] },
    { "id": "quicksand-quicksand", "heading": "Quicksand", "body": "Quicksand", "style": "humanist", "tags": ["wellness", "consumer", "soft"] },
    { "id": "mulish-mulish", "heading": "Mulish", "body": "Mulish", "style": "modern-minimal", "tags": ["fintech", "clean", "professional"] },
    { "id": "rubik-rubik", "heading": "Rubik", "body": "Rubik", "style": "humanist", "tags": ["saas", "accessible", "round"] },
    { "id": "albert-sans-albert-sans", "heading": "Albert Sans", "body": "Albert Sans", "style": "modern-minimal", "tags": ["nordic", "minimal", "clean"] },
    { "id": "hind-hind", "heading": "Hind", "body": "Hind", "style": "humanist", "tags": ["enterprise", "multilingual", "neutral"] },
    { "id": "epilogue-epilogue", "heading": "Epilogue", "body": "Epilogue", "style": "geometric", "tags": ["startup", "modern", "saas"] },
    { "id": "be-vietnam-pro-be-vietnam-pro", "heading": "Be Vietnam Pro", "body": "Be Vietnam Pro", "style": "humanist", "tags": ["saas", "clean", "tech"] }
  ]
}
